mpf/__init__.py
mpf/bisect.py
mpf/bitvector.py
mpf/floats.py
mpf/interval_q.py
mpf/rationals.py
pympf-1.0.4.dist-info/LICENSE
pympf-1.0.4.dist-info/METADATA
pympf-1.0.4.dist-info/WHEEL
pympf-1.0.4.dist-info/top_level.txt
pympf-1.0.4.dist-info/RECORD
