Metadata-Version: 2.1
Name: pympf
Version: 1.0.4
Summary: An arbitrary precision IEEE-754 implementation in Python
Home-page: https://github.com/florianschanda/PyMPF
Author: Florian Schanda
Author-email: florian@schanda.org.uk
License: UNKNOWN
Project-URL: Bug Tracker, https://github.com/florianschanda/PyMPF/issues
Project-URL: Documentation, https://florianschanda.github.io/PyMPF/
Project-URL: Source Code, https://github.com/florianschanda/PyMPF
Platform: UNKNOWN
Classifier: Development Status :: 5 - Production/Stable
Classifier: Intended Audience :: Developers
Classifier: Intended Audience :: Science/Research
Classifier: License :: OSI Approved :: GNU General Public License v3 or later (GPLv3+)
Classifier: Operating System :: OS Independent
Classifier: Programming Language :: Python :: 3
Classifier: Topic :: Scientific/Engineering :: Mathematics
Classifier: Topic :: Software Development :: Libraries
Classifier: Topic :: System :: Emulators
Requires-Python: >=3.5, <4
